airflow_supervisor/__init__.py
airflow_supervisor/airflow/__init__.py
airflow_supervisor/airflow/local.py
airflow_supervisor/airflow/ssh.py
airflow_supervisor/config/__init__.py
airflow_supervisor/config/supervisor.py
airflow_supervisor/config/supervisor_ssh.py
airflow_supervisor/config/task.py
airflow_supervisor/config/task_ssh.py
airflow_supervisor/tests/conftest.py
airflow_supervisor/tests/gen_test_pydantic.py
airflow_supervisor/tests/test_dag.py
airflow_supervisor/tests/test_nolocal.py
airflow_supervisor/tests/test_ssh.py
airflow_supervisor/tests/config/test_airflow.py
airflow_supervisor/tests/hydra/test_hydra.py
airflow_supervisor/tests/hydra/test_hydra_overrides.py
airflow_supervisor/tests/hydra/config/balancer.yaml
airflow_supervisor/tests/hydra/config/config.yaml
airflow_supervisor/tests/hydra/config/config_tasks.yaml
airflow_supervisor/tests/hydra/config/config_tasks_host.yaml
airflow_supervisor/tests/hydra/config/config_tasks_host_query.yaml
airflow_supervisor/tests/hydra/config/supervisor.yaml
airflow_supervisor/tests/hydra/config/inet_http_server/local.yaml
airflow_supervisor/tests/hydra/config/program/echo.yaml
airflow_supervisor/tests/hydra/config/program/sleep.yaml
airflow_supervisor/tests/hydra/config/rpcinterface/standard.yaml
airflow_supervisor-1.10.1.dist-info/METADATA
airflow_supervisor-1.10.1.dist-info/WHEEL
airflow_supervisor-1.10.1.dist-info/licenses/LICENSE
airflow_supervisor-1.10.1.dist-info/RECORD
